src/__init__.py
src/crypto_trader_analysis/__init__.py
src/crypto_trader_analysis/api/__init__.py
src/crypto_trader_analysis/api/asgi.py
src/crypto_trader_analysis/api/settings.py
src/crypto_trader_analysis/api/urls.py
src/crypto_trader_analysis/api/wsgi.py
src/crypto_trader_analysis/apps/__init__.py
src/crypto_trader_analysis/apps/learning/__init__.py
src/crypto_trader_analysis/apps/learning/models/__init__.py
src/crypto_trader_analysis/apps/learning/models/currency_json_generator.py
src/crypto_trader_analysis/apps/learning/models/ai/__init__.py
src/crypto_trader_analysis/apps/learning/models/ai/model_retriever.py
src/crypto_trader_analysis/apps/learning/models/ai/model_type.py
src/crypto_trader_analysis/apps/learning/models/ai/lstm/__init__.py
src/crypto_trader_analysis/apps/learning/models/ai/lstm/base_model.py
src/crypto_trader_analysis/apps/learning/models/ai/lstm/complex_lstm_model.py
src/crypto_trader_analysis/apps/learning/models/ai/lstm/lstm_model.py
src/crypto_trader_analysis/apps/learning/models/ai/lstm/layered/__init__.py
src/crypto_trader_analysis/apps/learning/models/ai/lstm/layered/complex_multi_layer_lstm_model.py
src/crypto_trader_analysis/apps/learning/models/ai/lstm/layered/multi_layer_base_model.py
src/crypto_trader_analysis/apps/learning/models/ai/lstm/layered/multi_layer_lstm_model.py
src/crypto_trader_analysis/apps/learning/models/data/__init__.py
src/crypto_trader_analysis/apps/learning/models/data/preprocessor.py
src/crypto_trader_analysis/apps/learning/models/database/__init__.py
src/crypto_trader_analysis/apps/learning/models/database/database.py
src/crypto_trader_analysis/apps/learning/models/database/query_load.py
src/crypto_trader_analysis/apps/learning/models/database/query_type.py
src/crypto_trader_analysis/apps/learning/models/prediction/__init__.py
src/crypto_trader_analysis/apps/learning/models/prediction/prediction.py
src/crypto_trader_analysis/apps/learning/models/prediction/predictions.py
crypto_trader_analysis-0.1.3.dist-info/METADATA
crypto_trader_analysis-0.1.3.dist-info/WHEEL
crypto_trader_analysis-0.1.3.dist-info/entry_points.txt
crypto_trader_analysis-0.1.3.dist-info/top_level.txt
crypto_trader_analysis-0.1.3.dist-info/RECORD
