Metadata-Version: 2.4
Name: crypto-trader-analysis
Version: 0.1.3
Summary: Analysis and ML components for the Crypto Trader platform (news sentiment, training, utilities).
Author-email: Oliver Lear Sigwarth <sigwarthsoftware@gmail.com>
License-Expression: LicenseRef-Proprietary
Project-URL: Homepage, https://github.com/theoliverlear/Crypto-Trader
Project-URL: Repository, https://github.com/theoliverlear/Crypto-Trader
Project-URL: Issues, https://github.com/theoliverlear/Crypto-Trader/issues
Keywords: crypto,trading,machine-learning,tensorflow,django,analysis,sentiment
Classifier: Development Status :: 3 - Alpha
Classifier: Intended Audience :: Developers
Classifier: Topic :: Scientific/Engineering :: Artificial Intelligence
Classifier: Topic :: Office/Business :: Financial :: Investment
Classifier: Programming Language :: Python
Classifier: Programming Language :: Python :: 3
Classifier: Programming Language :: Python :: 3 :: Only
Classifier: Programming Language :: Python :: 3.10
Classifier: Operating System :: OS Independent
Requires-Python: >=3.10
Requires-Dist: attrs>=23.0.0
Requires-Dist: requests>=2.31.0
Requires-Dist: beautifulsoup4>=4.12.0
Provides-Extra: web
Requires-Dist: Django>=5.1; extra == "web"
Provides-Extra: data
Requires-Dist: numpy>=1.23; extra == "data"
Requires-Dist: pandas>=2.0; extra == "data"
Provides-Extra: ml
Requires-Dist: numpy>=1.23; extra == "ml"
Requires-Dist: pandas>=2.0; extra == "ml"
Requires-Dist: tensorflow>=2.14; extra == "ml"
Provides-Extra: all
Requires-Dist: Django>=5.1; extra == "all"
Requires-Dist: numpy>=1.23; extra == "all"
Requires-Dist: pandas>=2.0; extra == "all"
Requires-Dist: tensorflow>=2.14; extra == "all"
